<item>
  <title>Retro Rabbit - EP 197 - Predictive Programming: Fight The Future!</title>
  <itunes:title>Retro Rabbit - Predictive Programming: Fight The Future!</itunes:title>
  <pubDate>Tue, 06 Jun 2023 03:18:00 +0000</pubDate>
  <guid isPermaLink="false"><![CDATA[17628a1b-8bb0-4b7f-937b-615c7d99c7a0]]></guid>
  <link><![CDATA[https://sites.libsyn.com/140084/retro-rabbit-ep-197-predictive-programming-fight-the-future]]></link>
  <itunes:image href="https://ssl-static.libsyn.com/p/assets/c/1/e/b/c1eb570ab9462fce16c3140a3186d450/Retro_Rabbit_3000_72.jpg"/>
  <description><![CDATA[<div class="DraftEditor-paragraphElement" data-block="true" data-editor="5rr2f" data-offset-key="2dn9f-0-0"> <div class= "public-DraftStyleDefault-block public-DraftStyleDefault-ltr" data-offset-key="2dn9f-0-0"><span data-offset-key= "2dn9f-0-0"><span data-text="true">Jason is too tired to write a real description so this episode is about Rawhead And/Or Bloody Bones and then we rant about Predictive Programming!</span></span></div> </div> <div class="DraftEditor-paragraphElement" data-block="true" data-editor="5rr2f" data-offset-key="435bn-0-0"> <div class= "public-DraftStyleDefault-block public-DraftStyleDefault-ltr" data-offset-key="435bn-0-0"><span data-offset-key= "435bn-0-0"> </span></div> </div> <div class="DraftEditor-paragraphElement" data-block="true" data-editor="5rr2f" data-offset-key="57qg8-0-0"> <div class= "public-DraftStyleDefault-block public-DraftStyleDefault-ltr" data-offset-key="57qg8-0-0"><span data-offset-key= "57qg8-0-0"><span data-text="true">Vote For Your Favorite Paranormal Podcast: Dead Rabbit Radio!</span></span></div> </div> <div class="DraftEditor-paragraphElement" data-block="true" data-editor="5rr2f" data-offset-key="8uqib-0-0"> <div class= "public-DraftStyleDefault-block public-DraftStyleDefault-ltr" data-offset-key="8uqib-0-0"><a class="sc-1bctqj2-0 iUIcXv" href= "https://paranormalitymag.com/vote25/"><span data-offset-key= "8uqib-0-0"><span data-text= "true">https://paranormalitymag.com/vote25/</span></span></a></div> </div> <div class="DraftEditor-paragraphElement" data-block="true" data-editor="5rr2f" data-offset-key="7ujqb-0-0"> <div class= "public-DraftStyleDefault-block public-DraftStyleDefault-ltr" data-offset-key="7ujqb-0-0"><span data-offset-key= "7ujqb-0-0"><span data-text="true">Patreon</span></span></div> </div> <div class="DraftEditor-paragraphElement" data-block="true" data-editor="5rr2f" data-offset-key="d5l9s-0-0"> <div class= "public-DraftStyleDefault-block public-DraftStyleDefault-ltr" data-offset-key="d5l9s-0-0"><a class="sc-1bctqj2-0 iUIcXv" href= "https://www.patreon.com/user?u=18482113"><span data-offset-key= "d5l9s-0-0"><span data-text= "true">https://www.patreon.com/user?u=18482113</span></span></a></div> </div> <div class="DraftEditor-paragraphElement" data-block="true" data-editor="5rr2f" data-offset-key="4g2f5-0-0"> <div class= "public-DraftStyleDefault-block public-DraftStyleDefault-ltr" data-offset-key="4g2f5-0-0"><span data-offset-key= "4g2f5-0-0"><span data-text="true">PayPal Donation Link</span></span></div> </div> <div class="DraftEditor-paragraphElement" data-block="true" data-editor="5rr2f" data-offset-key="ebtek-0-0"> <div class= "public-DraftStyleDefault-block public-DraftStyleDefault-ltr" data-offset-key="ebtek-0-0"><a class="sc-1bctqj2-0 iUIcXv" href= "https://tinyurl.com/mrxe36ph"><span data-offset-key= "ebtek-0-0"><span data-text= "true">https://tinyurl.com/mrxe36ph</span></span></a></div> </div> <div class="DraftEditor-paragraphElement" data-block="true" data-editor="5rr2f" data-offset-key="506t5-0-0"> <div class= "public-DraftStyleDefault-block public-DraftStyleDefault-ltr" data-offset-key="506t5-0-0"><span data-offset-key= "506t5-0-0"><span data-text="true">MERCH STORE!!!</span></span></div> </div> <div class="DraftEditor-paragraphElement" data-block="true" data-editor="5rr2f" data-offset-key="ckgn4-0-0"> <div class= "public-DraftStyleDefault-block public-DraftStyleDefault-ltr" data-offset-key="ckgn4-0-0"><a class="sc-1bctqj2-0 iUIcXv" href= "https://tinyurl.com/y8zam4o2"><span data-offset-key= "ckgn4-0-0"><span data-text= "true">https://tinyurl.com/y8zam4o2</span></span></a></div> </div> <div class="DraftEditor-paragraphElement" data-block="true" data-editor="5rr2f" data-offset-key="1q6r-0-0"> <div class= "public-DraftStyleDefault-block public-DraftStyleDefault-ltr" data-offset-key="1q6r-0-0"><span data-offset-key= "1q6r-0-0"><span data-text="true">Amazon Wish List</span></span></div> </div> <div class="DraftEditor-paragraphElement" data-block="true" data-editor="5rr2f" data-offset-key="chmdu-0-0"> <div class= "public-DraftStyleDefault-block public-DraftStyleDefault-ltr" data-offset-key="chmdu-0-0"><a class="sc-1bctqj2-0 iUIcXv" href= "https://www.amazon.com/hz/wishlist/ls/28CIOGSFRUXAD?ref_=wl_share"> <span data-offset-key="chmdu-0-0"><span data-text= "true">https://www.amazon.com/hz/wishlist/ls/28CIOGSFRUXAD?ref_=wl_share</span></span></a></div> </div> <div class="DraftEditor-paragraphElement" data-block="true" data-editor="5rr2f" data-offset-key="1j8i3-0-0"> <div class= "public-DraftStyleDefault-block public-DraftStyleDefault-ltr" data-offset-key="1j8i3-0-0"><span data-offset-key= "1j8i3-0-0"><span data-text="true">Dead Rabbit Radio Wiki</span></span></div> </div> <div class="DraftEditor-paragraphElement" data-block="true" data-editor="5rr2f" data-offset-key="fhvbs-0-0"> <div class= "public-DraftStyleDefault-block public-DraftStyleDefault-ltr" data-offset-key="fhvbs-0-0"><a class="sc-1bctqj2-0 iUIcXv" href= "https://deadrabbitradio.pods.monster/doku.php?id=Welcome"><span data-offset-key="fhvbs-0-0"> <span data-text= "true">https://deadrabbitradio.pods.monster/doku.php?id=Welcome</span></span></a></div> </div> <div class="DraftEditor-paragraphElement" data-block="true" data-editor="5rr2f" data-offset-key="5iv0j-0-0"> <div class= "public-DraftStyleDefault-block public-DraftStyleDefault-ltr" data-offset-key="5iv0j-0-0"><span data-offset-key= "5iv0j-0-0"> </span></div> </div> <div class="DraftEditor-paragraphElement" data-block="true" data-editor="5rr2f" data-offset-key="c70b1-0-0"> <div class= "public-DraftStyleDefault-block public-DraftStyleDefault-ltr" data-offset-key="c70b1-0-0"><span data-offset-key= "c70b1-0-0"><span data-text="true">Help Promote Dead Rabbit!</span></span></div> </div> <div class="DraftEditor-paragraphElement" data-block="true" data-editor="5rr2f" data-offset-key="74vvl-0-0"> <div class= "public-DraftStyleDefault-block public-DraftStyleDefault-ltr" data-offset-key="74vvl-0-0"><span data-offset-key= "74vvl-0-0"><span data-text="true">Dual Flyer</span></span></div> </div> <div class="DraftEditor-paragraphElement" data-block="true" data-editor="5rr2f" data-offset-key="asvc9-0-0"> <div class= "public-DraftStyleDefault-block public-DraftStyleDefault-ltr" data-offset-key="asvc9-0-0"><a class="sc-1bctqj2-0 iUIcXv" href= "https://i.imgur.com/OhuoI2v.jpg"><span data-offset-key= "asvc9-0-0"><span data-text= "true">https://i.imgur.com/OhuoI2v.jpg</span></span></a></div> </div> <div class="DraftEditor-paragraphElement" data-block="true" data-editor="5rr2f" data-offset-key="f99di-0-0"> <div class= "public-DraftStyleDefault-block public-DraftStyleDefault-ltr" data-offset-key="f99di-0-0"><span data-offset-key= "f99di-0-0"><span data-text="true">"As Above" Flyer</span></span></div> </div> <div class="DraftEditor-paragraphElement" data-block="true" data-editor="5rr2f" data-offset-key="67gro-0-0"> <div class= "public-DraftStyleDefault-block public-DraftStyleDefault-ltr" data-offset-key="67gro-0-0"><a class="sc-1bctqj2-0 iUIcXv" href= "https://i.imgur.com/yobMtUp.jpg"><span data-offset-key= "67gro-0-0"><span data-text= "true">https://i.imgur.com/yobMtUp.jpg</span></span></a></div> </div> <div class="DraftEditor-paragraphElement" data-block="true" data-editor="5rr2f" data-offset-key="9kbi2-0-0"> <div class= "public-DraftStyleDefault-block public-DraftStyleDefault-ltr" data-offset-key="9kbi2-0-0"><span data-offset-key= "9kbi2-0-0"><span data-text="true">“Alien Flyer” By TVP VT U</span></span></div> </div> <div class="DraftEditor-paragraphElement" data-block="true" data-editor="5rr2f" data-offset-key="613md-0-0"> <div class= "public-DraftStyleDefault-block public-DraftStyleDefault-ltr" data-offset-key="613md-0-0"><a class="sc-1bctqj2-0 iUIcXv" href= "https://imgur.com/gallery/aPN1Fnw"><span data-offset-key= "613md-0-0"><span data-text= "true">https://imgur.com/gallery/aPN1Fnw</span></span></a></div> </div> <div class="DraftEditor-paragraphElement" data-block="true" data-editor="5rr2f" data-offset-key="1805r-0-0"> <div class= "public-DraftStyleDefault-block public-DraftStyleDefault-ltr" data-offset-key="1805r-0-0"><span data-offset-key= "1805r-0-0"><span data-text="true">“QR Code Flyer” by Finn</span></span></div> </div> <div class="DraftEditor-paragraphElement" data-block="true" data-editor="5rr2f" data-offset-key="30dpi-0-0"> <div class= "public-DraftStyleDefault-block public-DraftStyleDefault-ltr" data-offset-key="30dpi-0-0"><a class="sc-1bctqj2-0 iUIcXv" href= "https://imgur.com/a/aYYUMAh"><span data-offset-key= "30dpi-0-0"><span data-text= "true">https://imgur.com/a/aYYUMAh</span></span></a></div> </div> <div class="DraftEditor-paragraphElement" data-block="true" data-editor="5rr2f" data-offset-key="1vlgq-0-0"> <div class= "public-DraftStyleDefault-block public-DraftStyleDefault-ltr" data-offset-key="1vlgq-0-0"><span data-offset-key= "1vlgq-0-0"> </span></div> </div> <div class="DraftEditor-paragraphElement" data-block="true" data-editor="5rr2f" data-offset-key="3ip65-0-0"> <div class= "public-DraftStyleDefault-block public-DraftStyleDefault-ltr" data-offset-key="3ip65-0-0"><span data-offset-key= "3ip65-0-0"><span data-text="true">Links:</span></span></div> </div> <div class="DraftEditor-paragraphElement" data-block="true" data-editor="5rr2f" data-offset-key="buvi1-0-0"> <div class= "public-DraftStyleDefault-block public-DraftStyleDefault-ltr" data-offset-key="buvi1-0-0"><span data-offset-key= "buvi1-0-0"><span data-text="true">Bloody Bones</span></span></div> </div> <div class="DraftEditor-paragraphElement" data-block="true" data-editor="5rr2f" data-offset-key="tf9n-0-0"> <div class= "public-DraftStyleDefault-block public-DraftStyleDefault-ltr" data-offset-key="tf9n-0-0"><a class="sc-1bctqj2-0 iUIcXv" href= "https://en.wikipedia.org/wiki/Bloody_Bones"><span data-offset-key= "tf9n-0-0"><span data-text= "true">https://en.wikipedia.org/wiki/Bloody_Bones</span></span></a></div> </div> <div class="DraftEditor-paragraphElement" data-block="true" data-editor="5rr2f" data-offset-key="45srd-0-0"> <div class= "public-DraftStyleDefault-block public-DraftStyleDefault-ltr" data-offset-key="45srd-0-0"><span data-offset-key= "45srd-0-0"><span data-text="true">Rawhead & Bloody Bones: Evolution of a 16th Century Bogeyman</span></span></div> </div> <div class="DraftEditor-paragraphElement" data-block="true" data-editor="5rr2f" data-offset-key="ejo6d-0-0"> <div class= "public-DraftStyleDefault-block public-DraftStyleDefault-ltr" data-offset-key="ejo6d-0-0"><a class="sc-1bctqj2-0 iUIcXv" href= "https://www.urbanghostsmedia.com/2016/11/rawhead-bloody-bones-bogeyman/"> <span data-offset-key="ejo6d-0-0"><span data-text= "true">https://www.urbanghostsmedia.com/2016/11/rawhead-bloody-bones-bogeyman/</span></span></a></div> </div> <div class="DraftEditor-paragraphElement" data-block="true" data-editor="5rr2f" data-offset-key="7hvgp-0-0"> <div class= "public-DraftStyleDefault-block public-DraftStyleDefault-ltr" data-offset-key="7hvgp-0-0"><span data-offset-key= "7hvgp-0-0"><span data-text="true">Rawhead and Bloody Bones</span></span></div> </div> <div class="DraftEditor-paragraphElement" data-block="true" data-editor="5rr2f" data-offset-key="3900t-0-0"> <div class= "public-DraftStyleDefault-block public-DraftStyleDefault-ltr" data-offset-key="3900t-0-0"><a class="sc-1bctqj2-0 iUIcXv" href= "https://maskofreason.wordpress.com/the-book-of-mysteries/know-your-ghosts/europe/rawhead-and-bloody-bones/"> <span data-offset-key="3900t-0-0"><span data-text= "true">https://maskofreason.wordpress.com/the-book-of-mysteries/know-your-ghosts/europe/rawhead-and-bloody-bones/</span></span></a></div> </div> <div class="DraftEditor-paragraphElement" data-block="true" data-editor="5rr2f" data-offset-key="el1pr-0-0"> <div class= "public-DraftStyleDefault-block public-DraftStyleDefault-ltr" data-offset-key="el1pr-0-0"><span data-offset-key= "el1pr-0-0"><span data-text="true">Bloody Bones: A History of Southern Scares</span></span></div> </div> <div class="DraftEditor-paragraphElement" data-block="true" data-editor="5rr2f" data-offset-key="5t1lp-0-0"> <div class= "public-DraftStyleDefault-block public-DraftStyleDefault-ltr" data-offset-key="5t1lp-0-0"><a class="sc-1bctqj2-0 iUIcXv" href= "https://deepsouthmag.com/2014/10/17/bloody-bones-a-history-of-southern-scares/"> <span data-offset-key="5t1lp-0-0"><span data-text= "true">https://deepsouthmag.com/2014/10/17/bloody-bones-a-history-of-southern-scares/</span></span></a></div> </div> <div class="DraftEditor-paragraphElement" data-block="true" data-editor="5rr2f" data-offset-key="ahcvg-0-0"> <div class= "public-DraftStyleDefault-block public-DraftStyleDefault-ltr" data-offset-key="ahcvg-0-0"><span data-offset-key= "ahcvg-0-0"><span data-text="true">Bloody Bones & GooGoo Eyes</span></span></div> </div> <div class="DraftEditor-paragraphElement" data-block="true" data-editor="5rr2f" data-offset-key="cb2sm-0-0"> <div class= "public-DraftStyleDefault-block public-DraftStyleDefault-ltr" data-offset-key="cb2sm-0-0"><a class="sc-1bctqj2-0 iUIcXv" href= "http://www.jalhost.net/Family_History/BloodyBones_GooGoo_Eyes.html"> <span data-offset-key="cb2sm-0-0"><span data-text= "true">http://www.jalhost.net/Family_History/BloodyBones_GooGoo_Eyes.html</span></span></a></div> </div> <div class="DraftEditor-paragraphElement" data-block="true" data-editor="5rr2f" data-offset-key="1sbai-0-0"> <div class= "public-DraftStyleDefault-block public-DraftStyleDefault-ltr" data-offset-key="1sbai-0-0"><span data-offset-key= "1sbai-0-0"><span data-text="true">Next 9/11 Revealed In Simpsons?</span></span></div> </div> <div class="DraftEditor-paragraphElement" data-block="true" data-editor="5rr2f" data-offset-key="d6vbg-0-0"> <div class= "public-DraftStyleDefault-block public-DraftStyleDefault-ltr" data-offset-key="d6vbg-0-0"><a class="sc-1bctqj2-0 iUIcXv" href= "https://beforeitsnews.com/v3/conspiracy-theories/2012/2129992.html"> <span data-offset-key="d6vbg-0-0"><span data-text= "true">https://beforeitsnews.com/v3/conspiracy-theories/2012/2129992.html</span></span></a></div> </div> <div class="DraftEditor-paragraphElement" data-block="true" data-editor="5rr2f" data-offset-key="3qgvb-0-0"> <div class= "public-DraftStyleDefault-block public-DraftStyleDefault-ltr" data-offset-key="3qgvb-0-0"><span data-offset-key= "3qgvb-0-0"><span data-text="true">5 reasons why “predictive programming” is psychologically implausible</span></span></div> </div> <div class="DraftEditor-paragraphElement" data-block="true" data-editor="5rr2f" data-offset-key="735ov-0-0"> <div class= "public-DraftStyleDefault-block public-DraftStyleDefault-ltr" data-offset-key="735ov-0-0"><a class="sc-1bctqj2-0 iUIcXv" href= "https://conspiracypsychology.com/2013/08/21/5-reasons-why-predictive-programming-is-psychologically-implausible/amp/"> <span data-offset-key="735ov-0-0"><span data-text= "true">https://conspiracypsychology.com/2013/08/21/5-reasons-why-predictive-programming-is-psychologically-implausible/amp/</span></span></a></div> </div> <div class="DraftEditor-paragraphElement" data-block="true" data-editor="5rr2f" data-offset-key="esic7-0-0"> <div class= "public-DraftStyleDefault-block public-DraftStyleDefault-ltr" data-offset-key="esic7-0-0"><span data-offset-key= "esic7-0-0"><span data-text="true">To Surveil with Love</span></span></div> </div> <div class="DraftEditor-paragraphElement" data-block="true" data-editor="5rr2f" data-offset-key="ff2fa-0-0"> <div class= "public-DraftStyleDefault-block public-DraftStyleDefault-ltr" data-offset-key="ff2fa-0-0"><a class="sc-1bctqj2-0 iUIcXv" href= "https://en.wikipedia.org/wiki/To_Surveil_with_Love"><span data-offset-key="ff2fa-0-0"> <span data-text= "true">https://en.wikipedia.org/wiki/To_Surveil_with_Love</span></span></a></div> </div> <div class="DraftEditor-paragraphElement" data-block="true" data-editor="5rr2f" data-offset-key="525j6-0-0"> <div class= "public-DraftStyleDefault-block public-DraftStyleDefault-ltr" data-offset-key="525j6-0-0"><span data-offset-key= "525j6-0-0"><span data-text="true">Hunger Games Predicts Death of Masculinity (2014)</span></span></div> </div> <div class="DraftEditor-paragraphElement" data-block="true" data-editor="5rr2f" data-offset-key="48drf-0-0"> <div class= "public-DraftStyleDefault-block public-DraftStyleDefault-ltr" data-offset-key="48drf-0-0"><a class="sc-1bctqj2-0 iUIcXv" href= "https://www.youtube.com/watch?v=ZcAVfHvIBns"><span data-offset-key="48drf-0-0"> <span data-text= "true">https://www.youtube.com/watch?v=ZcAVfHvIBns</span></span></a></div> </div> <div class="DraftEditor-paragraphElement" data-block="true" data-editor="5rr2f" data-offset-key="2trnc-0-0"> <div class= "public-DraftStyleDefault-block public-DraftStyleDefault-ltr" data-offset-key="2trnc-0-0"><span data-offset-key= "2trnc-0-0"><span data-text="true">Agenda 21 & 'The Hunger Games'</span></span></div> </div> <div class="DraftEditor-paragraphElement" data-block="true" data-editor="5rr2f" data-offset-key="coca1-0-0"> <div class= "public-DraftStyleDefault-block public-DraftStyleDefault-ltr" data-offset-key="coca1-0-0"><a class="sc-1bctqj2-0 iUIcXv" href= "https://www.youtube.com/watch?v=D4QXYe7VsXU"><span data-offset-key="coca1-0-0"> <span data-text= "true">https://www.youtube.com/watch?v=D4QXYe7VsXU</span></span></a></div> </div> <div class="DraftEditor-paragraphElement" data-block="true" data-editor="5rr2f" data-offset-key="r5hl-0-0"> <div class= "public-DraftStyleDefault-block public-DraftStyleDefault-ltr" data-offset-key="r5hl-0-0"><span data-offset-key= "r5hl-0-0"><span data-text="true">Predictive Programming in The Hunger Games</span></span></div> </div> <div class="DraftEditor-paragraphElement" data-block="true" data-editor="5rr2f" data-offset-key="dg2ms-0-0"> <div class= "public-DraftStyleDefault-block public-DraftStyleDefault-ltr" data-offset-key="dg2ms-0-0"><a class="sc-1bctqj2-0 iUIcXv" href= "http://www.libertarianprepper.com/predictive-programming-in-the-hunger-games/"> <span data-offset-key="dg2ms-0-0"><span data-text= "true">http://www.libertarianprepper.com/predictive-programming-in-the-hunger-games/</span></span></a></div> </div> <div class="DraftEditor-paragraphElement" data-block="true" data-editor="5rr2f" data-offset-key="cipts-0-0"> <div class= "public-DraftStyleDefault-block public-DraftStyleDefault-ltr" data-offset-key="cipts-0-0"><span data-offset-key= "cipts-0-0"><span data-text= "true">------------------------------------------------</span></span></div> </div> <div class="DraftEditor-paragraphElement" data-block="true" data-editor="5rr2f" data-offset-key="f77qb-0-0"> <div class= "public-DraftStyleDefault-block public-DraftStyleDefault-ltr" data-offset-key="f77qb-0-0"><span data-offset-key= "f77qb-0-0"><span data-text="true">Logo Art By Ash Black</span></span></div> </div> <div class="DraftEditor-paragraphElement" data-block="true" data-editor="5rr2f" data-offset-key="7m77g-0-0"> <div class= "public-DraftStyleDefault-block public-DraftStyleDefault-ltr" data-offset-key="7m77g-0-0"><span data-offset-key= "7m77g-0-0"><span data-text="true">Opening Song: "Atlantis Attacks"</span></span></div> </div> <div class="DraftEditor-paragraphElement" data-block="true" data-editor="5rr2f" data-offset-key="99mou-0-0"> <div class= "public-DraftStyleDefault-block public-DraftStyleDefault-ltr" data-offset-key="99mou-0-0"><span data-offset-key= "99mou-0-0"><span data-text="true">Closing Song: "Bella Royale"</span></span></div> </div> <div class="DraftEditor-paragraphElement" data-block="true" data-editor="5rr2f" data-offset-key="8r2iu-0-0"> <div class= "public-DraftStyleDefault-block public-DraftStyleDefault-ltr" data-offset-key="8r2iu-0-0"><span data-offset-key= "8r2iu-0-0"><span data-text="true">Music By Simple</span></span></div> </div> <div class="DraftEditor-paragraphElement" data-block="true" data-editor="5rr2f" data-offset-key="7ur9s-0-0"> <div class= "public-DraftStyleDefault-block public-DraftStyleDefault-ltr" data-offset-key="7ur9s-0-0"><span data-offset-key= "7ur9s-0-0"><span data-text="true">Rabbitron 3000 created by Eerbud</span></span></div> </div> <div class="DraftEditor-paragraphElement" data-block="true" data-editor="5rr2f" data-offset-key="9n3oi-0-0"> <div class= "public-DraftStyleDefault-block public-DraftStyleDefault-ltr" data-offset-key="9n3oi-0-0"><span data-offset-key= "9n3oi-0-0"><span data-text="true">Thanks to Chris K, Founder Of The Golden Rabbit Brigade</span></span></div> </div> <div class="DraftEditor-paragraphElement" data-block="true" data-editor="5rr2f" data-offset-key="4e9il-0-0"> <div class= "public-DraftStyleDefault-block public-DraftStyleDefault-ltr" data-offset-key="4e9il-0-0"><span data-offset-key= "4e9il-0-0"><span data-text="true">Dead Rabbit Archivist Some Weirdo On Twitter AKA Jack</span></span></div> </div> <div class="DraftEditor-paragraphElement" data-block="true" data-editor="5rr2f" data-offset-key="3oe6n-0-0"> <div class= "public-DraftStyleDefault-block public-DraftStyleDefault-ltr" data-offset-key="3oe6n-0-0"><span data-offset-key= "3oe6n-0-0"><span data-text="true">YouTube Champ Stewart Meatball</span></span></div> </div> <div class="DraftEditor-paragraphElement" data-block="true" data-editor="5rr2f" data-offset-key="d9nqj-0-0"> <div class= "public-DraftStyleDefault-block public-DraftStyleDefault-ltr" data-offset-key="d9nqj-0-0"><span data-offset-key= "d9nqj-0-0"><span data-text="true">The Haunted Mic Arm provided by Chyme Chili</span></span></div> </div> <div class="DraftEditor-paragraphElement" data-block="true" data-editor="5rr2f" data-offset-key="9ht1u-0-0"> <div class= "public-DraftStyleDefault-block public-DraftStyleDefault-ltr" data-offset-key="9ht1u-0-0"><span data-offset-key= "9ht1u-0-0"><span data-text="true">The Golden Rabbit Army: Fabio N, Chyme Chili, Greg Gourley</span></span></div> </div> <div class="DraftEditor-paragraphElement" data-block="true" data-editor="5rr2f" data-offset-key="d6fgd-0-0"> <div class= "public-DraftStyleDefault-block public-DraftStyleDefault-ltr" data-offset-key="d6fgd-0-0"><span data-offset-key= "d6fgd-0-0"><span data-text="true">Wiki by Germ</span></span></div> </div> <div class="DraftEditor-paragraphElement" data-block="true" data-editor="5rr2f" data-offset-key="27kes-0-0"> <div class= "public-DraftStyleDefault-block public-DraftStyleDefault-ltr" data-offset-key="27kes-0-0"><a class="sc-1bctqj2-0 iUIcXv" href= "http://www.deadrabbit.com/"><span data-offset-key= "27kes-0-0"><span data-text= "true">http://www.DeadRabbit.com</span></span></a></div> </div> <div class="DraftEditor-paragraphElement" data-block="true" data-editor="5rr2f" data-offset-key="3b3p4-0-0"> <div class= "public-DraftStyleDefault-block public-DraftStyleDefault-ltr" data-offset-key="3b3p4-0-0"><span data-offset-key= "3b3p4-0-0"><span data-text="true">Email:</span></span> <a class= "sc-1bctqj2-0 iUIcXv" href= "mailto:DeadRabbitRadio@gmail.com"><span data-offset-key= "3b3p4-1-0"><span data-text= "true">DeadRabbitRadio@gmail.com</span></span></a></div> </div> <div class="DraftEditor-paragraphElement" data-block="true" data-editor="5rr2f" data-offset-key="ampt6-0-0"> <div class= "public-DraftStyleDefault-block public-DraftStyleDefault-ltr" data-offset-key="ampt6-0-0"><span data-offset-key= "ampt6-0-0"><span data-text="true">Twitter: @DeadRabbitRadio</span></span></div> </div> <div class="DraftEditor-paragraphElement" data-block="true" data-editor="5rr2f" data-offset-key="74evd-0-0"> <div class= "public-DraftStyleDefault-block public-DraftStyleDefault-ltr" data-offset-key="74evd-0-0"><span data-offset-key= "74evd-0-0"><span data-text="true">Facebook:</span></span> <a class="sc-1bctqj2-0 iUIcXv" href= "http://www.facebook.com/DeadRabbitRadio"><span data-offset-key= "74evd-1-0"><span data-text= "true">www.Facebook.com/DeadRabbitRadio</span></span></a></div> </div> <div class="DraftEditor-paragraphElement" data-block="true" data-editor="5rr2f" data-offset-key="40hqt-0-0"> <div class= "public-DraftStyleDefault-block public-DraftStyleDefault-ltr" data-offset-key="40hqt-0-0"><span data-offset-key= "40hqt-0-0"><span data-text="true">TikTok:</span></span> <a class= "sc-1bctqj2-0 iUIcXv" href= "https://www.tiktok.com/@deadrabbitradio"><span data-offset-key= "40hqt-1-0"><span data-text= "true">https://www.tiktok.com/@deadrabbitradio</span></span></a></div> </div> <div class="DraftEditor-paragraphElement" data-block="true" data-editor="5rr2f" data-offset-key="br1l9-0-0"> <div class= "public-DraftStyleDefault-block public-DraftStyleDefault-ltr" data-offset-key="br1l9-0-0"><span data-offset-key= "br1l9-0-0"><span data-text="true">Dead Rabbit Radio Subreddit:</span></span> <a class="sc-1bctqj2-0 iUIcXv" href= "https://www.reddit.com/r/DeadRabbitRadio/"><span data-offset-key= "br1l9-1-0"><span data-text= "true">https://www.reddit.com/r/DeadRabbitRadio/</span></span></a></div> </div> <div class="DraftEditor-paragraphElement" data-block="true" data-editor="5rr2f" data-offset-key="7r9ct-0-0"> <div class= "public-DraftStyleDefault-block public-DraftStyleDefault-ltr" data-offset-key="7r9ct-0-0"><span data-offset-key= "7r9ct-0-0"><span data-text="true">Paranormal News Subreddit:</span></span> <a class="sc-1bctqj2-0 iUIcXv" href= "https://www.reddit.com/r/ParanormalNews/"><span data-offset-key= "7r9ct-1-0"><span data-text= "true">https://www.reddit.com/r/ParanormalNews/</span></span></a></div> </div> <div class="DraftEditor-paragraphElement" data-block="true" data-editor="5rr2f" data-offset-key="bmvtk-0-0"> <div class= "public-DraftStyleDefault-block public-DraftStyleDefault-ltr" data-offset-key="bmvtk-0-0"><span data-offset-key= "bmvtk-0-0"> </span></div> </div> <div class="DraftEditor-paragraphElement" data-block="true" data-editor="5rr2f" data-offset-key="b3vu4-0-0"> <div class= "public-DraftStyleDefault-block public-DraftStyleDefault-ltr" data-offset-key="b3vu4-0-0"><span data-offset-key= "b3vu4-0-0"><span data-text="true">Mailing Address:</span></span></div> </div> <div class="DraftEditor-paragraphElement" data-block="true" data-editor="5rr2f" data-offset-key="e1qp6-0-0"> <div class= "public-DraftStyleDefault-block public-DraftStyleDefault-ltr" data-offset-key="e1qp6-0-0"><span data-offset-key= "e1qp6-0-0"><span data-text="true">Jason Carpenter</span></span></div> </div> <div class="DraftEditor-paragraphElement" data-block="true" data-editor="5rr2f" data-offset-key="6194c-0-0"> <div class= "public-DraftStyleDefault-block public-DraftStyleDefault-ltr" data-offset-key="6194c-0-0"><span data-offset-key= "6194c-0-0"><span data-text="true">PO Box 1363</span></span></div> </div> <div class="DraftEditor-paragraphElement" data-block="true" data-editor="5rr2f" data-offset-key="85lu0-0-0"> <div class= "public-DraftStyleDefault-block public-DraftStyleDefault-ltr" data-offset-key="85lu0-0-0"><span data-offset-key= "85lu0-0-0"><span data-text="true">Hood River, OR 97031</span></span></div> </div> <div class="DraftEditor-paragraphElement" data-block="true" data-editor="5rr2f" data-offset-key="e5pmk-0-0"> <div class= "public-DraftStyleDefault-block public-DraftStyleDefault-ltr" data-offset-key="e5pmk-0-0"><span data-offset-key= "e5pmk-0-0"><span data-text="true">Paranormal, Conspiracy, and True Crime news as it happens! Jason Carpenter breaks the stories they'll be talking about tomorrow, assuming the world doesn't end today.</span></span></div> </div> <div class="DraftEditor-paragraphElement" data-block="true" data-editor="5rr2f" data-offset-key="9p8gn-0-0"> <div class= "public-DraftStyleDefault-block public-DraftStyleDefault-ltr" data-offset-key="9p8gn-0-0"><span data-offset-key= "9p8gn-0-0"><span data-text="true">All Contents Of This Podcast Copyright Jason Carpenter 2018 - 2023</span></span></div> </div>]]></description>
  <content:encoded><![CDATA[ Jason is too tired to write a real description so this episode is about Rawhead And/Or Bloody Bones and then we rant about Predictive Programming!       Vote For Your Favorite Paranormal Podcast: Dead Rabbit Radio!   <a class="sc-1bctqj2-0 iUIcXv" href= "https://paranormalitymag.com/vote25/">https://paranormalitymag.com/vote25/</a>   Patreon   <a class="sc-1bctqj2-0 iUIcXv" href= "https://www.patreon.com/user?u=18482113">https://www.patreon.com/user?u=18482113</a>   PayPal Donation Link   <a class="sc-1bctqj2-0 iUIcXv" href= "https://tinyurl.com/mrxe36ph">https://tinyurl.com/mrxe36ph</a>   MERCH STORE!!!   <a class="sc-1bctqj2-0 iUIcXv" href= "https://tinyurl.com/y8zam4o2">https://tinyurl.com/y8zam4o2</a>   Amazon Wish List   <a class="sc-1bctqj2-0 iUIcXv" href= "https://www.amazon.com/hz/wishlist/ls/28CIOGSFRUXAD?ref_=wl_share"> https://www.amazon.com/hz/wishlist/ls/28CIOGSFRUXAD?ref_=wl_share</a>   Dead Rabbit Radio Wiki   <a class="sc-1bctqj2-0 iUIcXv" href= "https://deadrabbitradio.pods.monster/doku.php?id=Welcome"> https://deadrabbitradio.pods.monster/doku.php?id=Welcome</a>       Help Promote Dead Rabbit!   Dual Flyer   <a class="sc-1bctqj2-0 iUIcXv" href= "https://i.imgur.com/OhuoI2v.jpg">https://i.imgur.com/OhuoI2v.jpg</a>   "As Above" Flyer   <a class="sc-1bctqj2-0 iUIcXv" href= "https://i.imgur.com/yobMtUp.jpg">https://i.imgur.com/yobMtUp.jpg</a>   “Alien Flyer” By TVP VT U   <a class="sc-1bctqj2-0 iUIcXv" href= "https://imgur.com/gallery/aPN1Fnw">https://imgur.com/gallery/aPN1Fnw</a>   “QR Code Flyer” by Finn   <a class="sc-1bctqj2-0 iUIcXv" href= "https://imgur.com/a/aYYUMAh">https://imgur.com/a/aYYUMAh</a>       Links:   Bloody Bones   <a class="sc-1bctqj2-0 iUIcXv" href= "https://en.wikipedia.org/wiki/Bloody_Bones">https://en.wikipedia.org/wiki/Bloody_Bones</a>   Rawhead & Bloody Bones: Evolution of a 16th Century Bogeyman   <a class="sc-1bctqj2-0 iUIcXv" href= "https://www.urbanghostsmedia.com/2016/11/rawhead-bloody-bones-bogeyman/"> https://www.urbanghostsmedia.com/2016/11/rawhead-bloody-bones-bogeyman/</a>   Rawhead and Bloody Bones   <a class="sc-1bctqj2-0 iUIcXv" href= "https://maskofreason.wordpress.com/the-book-of-mysteries/know-your-ghosts/europe/rawhead-and-bloody-bones/"> https://maskofreason.wordpress.com/the-book-of-mysteries/know-your-ghosts/europe/rawhead-and-bloody-bones/</a>   Bloody Bones: A History of Southern Scares   <a class="sc-1bctqj2-0 iUIcXv" href= "https://deepsouthmag.com/2014/10/17/bloody-bones-a-history-of-southern-scares/"> https://deepsouthmag.com/2014/10/17/bloody-bones-a-history-of-southern-scares/</a>   Bloody Bones & GooGoo Eyes   <a class="sc-1bctqj2-0 iUIcXv" href= "http://www.jalhost.net/Family_History/BloodyBones_GooGoo_Eyes.html"> http://www.jalhost.net/Family_History/BloodyBones_GooGoo_Eyes.html</a>   Next 9/11 Revealed In Simpsons?   <a class="sc-1bctqj2-0 iUIcXv" href= "https://beforeitsnews.com/v3/conspiracy-theories/2012/2129992.html"> https://beforeitsnews.com/v3/conspiracy-theories/2012/2129992.html</a>   5 reasons why “predictive programming” is psychologically implausible   <a class="sc-1bctqj2-0 iUIcXv" href= "https://conspiracypsychology.com/2013/08/21/5-reasons-why-predictive-programming-is-psychologically-implausible/amp/"> https://conspiracypsychology.com/2013/08/21/5-reasons-why-predictive-programming-is-psychologically-implausible/amp/</a>   To Surveil with Love   <a class="sc-1bctqj2-0 iUIcXv" href= "https://en.wikipedia.org/wiki/To_Surveil_with_Love"> https://en.wikipedia.org/wiki/To_Surveil_with_Love</a>   Hunger Games Predicts Death of Masculinity (2014)   <a class="sc-1bctqj2-0 iUIcXv" href= "https://www.youtube.com/watch?v=ZcAVfHvIBns"> https://www.youtube.com/watch?v=ZcAVfHvIBns</a>   Agenda 21 & 'The Hunger Games'   <a class="sc-1bctqj2-0 iUIcXv" href= "https://www.youtube.com/watch?v=D4QXYe7VsXU"> https://www.youtube.com/watch?v=D4QXYe7VsXU</a>   Predictive Programming in The Hunger Games   <a class="sc-1bctqj2-0 iUIcXv" href= "http://www.libertarianprepper.com/predictive-programming-in-the-hunger-games/"> http://www.libertarianprepper.com/predictive-programming-in-the-hunger-games/</a>   ------------------------------------------------   Logo Art By Ash Black   Opening Song: "Atlantis Attacks"   Closing Song: "Bella Royale"   Music By Simple   Rabbitron 3000 created by Eerbud   Thanks to Chris K, Founder Of The Golden Rabbit Brigade   Dead Rabbit Archivist Some Weirdo On Twitter AKA Jack   YouTube Champ Stewart Meatball   The Haunted Mic Arm provided by Chyme Chili   The Golden Rabbit Army: Fabio N, Chyme Chili, Greg Gourley   Wiki by Germ   <a class="sc-1bctqj2-0 iUIcXv" href= "http://www.deadrabbit.com/">http://www.DeadRabbit.com</a>   Email: <a class= "sc-1bctqj2-0 iUIcXv" href= "mailto:DeadRabbitRadio@gmail.com">DeadRabbitRadio@gmail.com</a>   Twitter: @DeadRabbitRadio   Facebook: <a class="sc-1bctqj2-0 iUIcXv" href= "http://www.facebook.com/DeadRabbitRadio">www.Facebook.com/DeadRabbitRadio</a>   TikTok: <a class= "sc-1bctqj2-0 iUIcXv" href= "https://www.tiktok.com/@deadrabbitradio">https://www.tiktok.com/@deadrabbitradio</a>   Dead Rabbit Radio Subreddit: <a class="sc-1bctqj2-0 iUIcXv" href= "https://www.reddit.com/r/DeadRabbitRadio/">https://www.reddit.com/r/DeadRabbitRadio/</a>   Paranormal News Subreddit: <a class="sc-1bctqj2-0 iUIcXv" href= "https://www.reddit.com/r/ParanormalNews/">https://www.reddit.com/r/ParanormalNews/</a>       Mailing Address:   Jason Carpenter   PO Box 1363   Hood River, OR 97031   Paranormal, Conspiracy, and True Crime news as it happens! Jason Carpenter breaks the stories they'll be talking about tomorrow, assuming the world doesn't end today.   All Contents Of This Podcast Copyright Jason Carpenter 2018 - 2023 ]]></content:encoded>
  <enclosure length="27408603" type="audio/mpeg" url="https://chtbl.com/track/E2D25/dts.podtrac.com/redirect.mp3/pdcn.co/e/traffic.libsyn.com/secure/deadrabbitradio/Retro_Rabbit_023_EP_197.mp3?dest-id=877154"/>
  <itunes:duration>32:38</itunes:duration>
  <itunes:explicit>true</itunes:explicit>
  <itunes:keywords/>
  <itunes:subtitle><![CDATA[Jason is too tired to write a real description so this episode is about Rawhead And/Or Bloody Bones and then we rant about Predictive Programming!       Vote For Your Favorite Paranormal Podcast: Dead Rabbit Radio!      Patreon      PayPal...]]></itunes:subtitle>
  <itunes:episodeType>full</itunes:episodeType>
  <itunes:author>Jason Carpenter</itunes:author>
</item>