<item>
  <title>EP 1083 - Are YOU The Next Pigman Of Vermont?!?</title>
  <itunes:title>Are YOU The Next Pigman Of Vermont?!?</itunes:title>
  <pubDate>Wed, 17 May 2023 05:35:00 +0000</pubDate>
  <guid isPermaLink="false"><![CDATA[8d882c24-333b-4897-8588-a6307354717c]]></guid>
  <link><![CDATA[https://sites.libsyn.com/140084/ep-1083-are-you-the-next-pigman-of-vermont]]></link>
  <itunes:image href="https://ssl-static.libsyn.com/p/assets/f/e/7/0/fe70b120b968a6b4a04421dee9605cbd/Paranormal_Podcast_3000_72.jpg"/>
  <description><![CDATA[<div class="DraftEditor-paragraphElement" data-block="true" data-editor="f6cv1" data-offset-key="dhonj-0-0"> <div class= "public-DraftStyleDefault-block public-DraftStyleDefault-ltr" data-offset-key="dhonj-0-0"><span data-offset-key= "dhonj-0-0"><span data-text="true">A woman deflates/The Northfield Pigman attacks!</span></span></div> </div> <div class="DraftEditor-paragraphElement" data-block="true" data-editor="f6cv1" data-offset-key="1e60p-0-0"> <div class= "public-DraftStyleDefault-block public-DraftStyleDefault-ltr" data-offset-key="1e60p-0-0"><span data-offset-key= "1e60p-0-0"> </span></div> </div> <div class="DraftEditor-paragraphElement" data-block="true" data-editor="f6cv1" data-offset-key="4tld0-0-0"> <div class= "public-DraftStyleDefault-block public-DraftStyleDefault-ltr" data-offset-key="4tld0-0-0"><span data-offset-key= "4tld0-0-0"><span data-text="true">Vote For Your Favorite Paranormal Podcast: Dead Rabbit Radio!</span></span></div> </div> <div class="DraftEditor-paragraphElement" data-block="true" data-editor="f6cv1" data-offset-key="b4ti0-0-0"> <div class= "public-DraftStyleDefault-block public-DraftStyleDefault-ltr" data-offset-key="b4ti0-0-0"><a class="sc-1bctqj2-0 iUIcXv" href= "https://paranormalitymag.com/vote25/"><span data-offset-key= "b4ti0-0-0"><span data-text= "true">https://paranormalitymag.com/vote25/</span></span></a></div> </div> <div class="DraftEditor-paragraphElement" data-block="true" data-editor="f6cv1" data-offset-key="creco-0-0"> <div class= "public-DraftStyleDefault-block public-DraftStyleDefault-ltr" data-offset-key="creco-0-0"><span data-offset-key= "creco-0-0"><span data-text="true">Patreon</span></span></div> </div> <div class="DraftEditor-paragraphElement" data-block="true" data-editor="f6cv1" data-offset-key="5vc20-0-0"> <div class= "public-DraftStyleDefault-block public-DraftStyleDefault-ltr" data-offset-key="5vc20-0-0"><a class="sc-1bctqj2-0 iUIcXv" href= "https://www.patreon.com/user?u=18482113"><span data-offset-key= "5vc20-0-0"><span data-text= "true">https://www.patreon.com/user?u=18482113</span></span></a></div> </div> <div class="DraftEditor-paragraphElement" data-block="true" data-editor="f6cv1" data-offset-key="1p54d-0-0"> <div class= "public-DraftStyleDefault-block public-DraftStyleDefault-ltr" data-offset-key="1p54d-0-0"><span data-offset-key= "1p54d-0-0"><span data-text="true">PayPal Donation Link</span></span></div> </div> <div class="DraftEditor-paragraphElement" data-block="true" data-editor="f6cv1" data-offset-key="1h03k-0-0"> <div class= "public-DraftStyleDefault-block public-DraftStyleDefault-ltr" data-offset-key="1h03k-0-0"><a class="sc-1bctqj2-0 iUIcXv" href= "https://tinyurl.com/mrxe36ph"><span data-offset-key= "1h03k-0-0"><span data-text= "true">https://tinyurl.com/mrxe36ph</span></span></a></div> </div> <div class="DraftEditor-paragraphElement" data-block="true" data-editor="f6cv1" data-offset-key="2jpoo-0-0"> <div class= "public-DraftStyleDefault-block public-DraftStyleDefault-ltr" data-offset-key="2jpoo-0-0"><span data-offset-key= "2jpoo-0-0"><span data-text="true">MERCH STORE!!!</span></span></div> </div> <div class="DraftEditor-paragraphElement" data-block="true" data-editor="f6cv1" data-offset-key="f5hvp-0-0"> <div class= "public-DraftStyleDefault-block public-DraftStyleDefault-ltr" data-offset-key="f5hvp-0-0"><a class="sc-1bctqj2-0 iUIcXv" href= "https://tinyurl.com/y8zam4o2"><span data-offset-key= "f5hvp-0-0"><span data-text= "true">https://tinyurl.com/y8zam4o2</span></span></a></div> </div> <div class="DraftEditor-paragraphElement" data-block="true" data-editor="f6cv1" data-offset-key="6dbe1-0-0"> <div class= "public-DraftStyleDefault-block public-DraftStyleDefault-ltr" data-offset-key="6dbe1-0-0"><span data-offset-key= "6dbe1-0-0"><span data-text="true">Amazon Wish List</span></span></div> </div> <div class="DraftEditor-paragraphElement" data-block="true" data-editor="f6cv1" data-offset-key="9sfvu-0-0"> <div class= "public-DraftStyleDefault-block public-DraftStyleDefault-ltr" data-offset-key="9sfvu-0-0"><a class="sc-1bctqj2-0 iUIcXv" href= "https://www.amazon.com/hz/wishlist/ls/28CIOGSFRUXAD?ref_=wl_share"> <span data-offset-key="9sfvu-0-0"><span data-text= "true">https://www.amazon.com/hz/wishlist/ls/28CIOGSFRUXAD?ref_=wl_share</span></span></a></div> </div> <div class="DraftEditor-paragraphElement" data-block="true" data-editor="f6cv1" data-offset-key="2i39u-0-0"> <div class= "public-DraftStyleDefault-block public-DraftStyleDefault-ltr" data-offset-key="2i39u-0-0"><span data-offset-key= "2i39u-0-0"><span data-text="true">Dead Rabbit Radio Wiki</span></span></div> </div> <div class="DraftEditor-paragraphElement" data-block="true" data-editor="f6cv1" data-offset-key="et1f8-0-0"> <div class= "public-DraftStyleDefault-block public-DraftStyleDefault-ltr" data-offset-key="et1f8-0-0"><a class="sc-1bctqj2-0 iUIcXv" href= "https://deadrabbitradio.pods.monster/doku.php?id=Welcome"><span data-offset-key="et1f8-0-0"> <span data-text= "true">https://deadrabbitradio.pods.monster/doku.php?id=Welcome</span></span></a></div> </div> <div class="DraftEditor-paragraphElement" data-block="true" data-editor="f6cv1" data-offset-key="3tqrt-0-0"> <div class= "public-DraftStyleDefault-block public-DraftStyleDefault-ltr" data-offset-key="3tqrt-0-0"><span data-offset-key= "3tqrt-0-0"> </span></div> </div> <div class="DraftEditor-paragraphElement" data-block="true" data-editor="f6cv1" data-offset-key="56i5r-0-0"> <div class= "public-DraftStyleDefault-block public-DraftStyleDefault-ltr" data-offset-key="56i5r-0-0"><span data-offset-key= "56i5r-0-0"><span data-text="true">Help Promote Dead Rabbit!</span></span></div> </div> <div class="DraftEditor-paragraphElement" data-block="true" data-editor="f6cv1" data-offset-key="c54i2-0-0"> <div class= "public-DraftStyleDefault-block public-DraftStyleDefault-ltr" data-offset-key="c54i2-0-0"><span data-offset-key= "c54i2-0-0"><span data-text="true">Dual Flyer</span></span></div> </div> <div class="DraftEditor-paragraphElement" data-block="true" data-editor="f6cv1" data-offset-key="eve28-0-0"> <div class= "public-DraftStyleDefault-block public-DraftStyleDefault-ltr" data-offset-key="eve28-0-0"><a class="sc-1bctqj2-0 iUIcXv" href= "https://i.imgur.com/OhuoI2v.jpg"><span data-offset-key= "eve28-0-0"><span data-text= "true">https://i.imgur.com/OhuoI2v.jpg</span></span></a></div> </div> <div class="DraftEditor-paragraphElement" data-block="true" data-editor="f6cv1" data-offset-key="1m5o8-0-0"> <div class= "public-DraftStyleDefault-block public-DraftStyleDefault-ltr" data-offset-key="1m5o8-0-0"><span data-offset-key= "1m5o8-0-0"><span data-text="true">"As Above" Flyer</span></span></div> </div> <div class="DraftEditor-paragraphElement" data-block="true" data-editor="f6cv1" data-offset-key="ba2k0-0-0"> <div class= "public-DraftStyleDefault-block public-DraftStyleDefault-ltr" data-offset-key="ba2k0-0-0"><a class="sc-1bctqj2-0 iUIcXv" href= "https://i.imgur.com/yobMtUp.jpg"><span data-offset-key= "ba2k0-0-0"><span data-text= "true">https://i.imgur.com/yobMtUp.jpg</span></span></a></div> </div> <div class="DraftEditor-paragraphElement" data-block="true" data-editor="f6cv1" data-offset-key="fuoai-0-0"> <div class= "public-DraftStyleDefault-block public-DraftStyleDefault-ltr" data-offset-key="fuoai-0-0"><span data-offset-key= "fuoai-0-0"><span data-text="true">“Alien Flyer” By TVP VT U</span></span></div> </div> <div class="DraftEditor-paragraphElement" data-block="true" data-editor="f6cv1" data-offset-key="7ovh0-0-0"> <div class= "public-DraftStyleDefault-block public-DraftStyleDefault-ltr" data-offset-key="7ovh0-0-0"><a class="sc-1bctqj2-0 iUIcXv" href= "https://imgur.com/gallery/aPN1Fnw"><span data-offset-key= "7ovh0-0-0"><span data-text= "true">https://imgur.com/gallery/aPN1Fnw</span></span></a></div> </div> <div class="DraftEditor-paragraphElement" data-block="true" data-editor="f6cv1" data-offset-key="f92hq-0-0"> <div class= "public-DraftStyleDefault-block public-DraftStyleDefault-ltr" data-offset-key="f92hq-0-0"><span data-offset-key= "f92hq-0-0"><span data-text="true">“QR Code Flyer” by Finn</span></span></div> </div> <div class="DraftEditor-paragraphElement" data-block="true" data-editor="f6cv1" data-offset-key="btq5m-0-0"> <div class= "public-DraftStyleDefault-block public-DraftStyleDefault-ltr" data-offset-key="btq5m-0-0"><a class="sc-1bctqj2-0 iUIcXv" href= "https://imgur.com/a/aYYUMAh"><span data-offset-key= "btq5m-0-0"><span data-text= "true">https://imgur.com/a/aYYUMAh</span></span></a></div> </div> <div class="DraftEditor-paragraphElement" data-block="true" data-editor="f6cv1" data-offset-key="d2nhp-0-0"> <div class= "public-DraftStyleDefault-block public-DraftStyleDefault-ltr" data-offset-key="d2nhp-0-0"><span data-offset-key= "d2nhp-0-0"> </span></div> </div> <div class="DraftEditor-paragraphElement" data-block="true" data-editor="f6cv1" data-offset-key="a75f5-0-0"> <div class= "public-DraftStyleDefault-block public-DraftStyleDefault-ltr" data-offset-key="a75f5-0-0"><span data-offset-key= "a75f5-0-0"><span data-text="true">Links:</span></span></div> </div> <div class="DraftEditor-paragraphElement" data-block="true" data-editor="f6cv1" data-offset-key="ti7a-0-0"> <div class= "public-DraftStyleDefault-block public-DraftStyleDefault-ltr" data-offset-key="ti7a-0-0"><span data-offset-key= "ti7a-0-0"><span data-text="true">EP 310 - The Curse Of The Pigman: An Interactive Adventure! (Pig Man episode)</span></span></div> </div> <div class="DraftEditor-paragraphElement" data-block="true" data-editor="f6cv1" data-offset-key="8t83c-0-0"> <div class= "public-DraftStyleDefault-block public-DraftStyleDefault-ltr" data-offset-key="8t83c-0-0"><a class="sc-1bctqj2-0 iUIcXv" href= "https://deadrabbitradio.libsyn.com/ep-310-the-curse-of-the-pigman-an-interactive-adventure"> <span data-offset-key="8t83c-0-0"><span data-text= "true">https://deadrabbitradio.libsyn.com/ep-310-the-curse-of-the-pigman-an-interactive-adventure</span></span></a></div> </div> <div class="DraftEditor-paragraphElement" data-block="true" data-editor="f6cv1" data-offset-key="esvik-0-0"> <div class= "public-DraftStyleDefault-block public-DraftStyleDefault-ltr" data-offset-key="esvik-0-0"><span data-offset-key= "esvik-0-0"><span data-text="true">EP 488 - Attack Of The Pig Lady! (Pig Man episode)</span></span></div> </div> <div class="DraftEditor-paragraphElement" data-block="true" data-editor="f6cv1" data-offset-key="7ja2a-0-0"> <div class= "public-DraftStyleDefault-block public-DraftStyleDefault-ltr" data-offset-key="7ja2a-0-0"><a class="sc-1bctqj2-0 iUIcXv" href= "https://deadrabbitradio.libsyn.com/ep-488-attack-of-the-pig-lady"><span data-offset-key="7ja2a-0-0"> <span data-text= "true">https://deadrabbitradio.libsyn.com/ep-488-attack-of-the-pig-lady</span></span></a></div> </div> <div class="DraftEditor-paragraphElement" data-block="true" data-editor="f6cv1" data-offset-key="91fsa-0-0"> <div class= "public-DraftStyleDefault-block public-DraftStyleDefault-ltr" data-offset-key="91fsa-0-0"><span data-offset-key= "91fsa-0-0"><span data-text="true">EP 683 - The Pig Man Of Chino Hills Is Under Your Bed!</span></span></div> </div> <div class="DraftEditor-paragraphElement" data-block="true" data-editor="f6cv1" data-offset-key="fvvrs-0-0"> <div class= "public-DraftStyleDefault-block public-DraftStyleDefault-ltr" data-offset-key="fvvrs-0-0"><a class="sc-1bctqj2-0 iUIcXv" href= "https://deadrabbitradio.libsyn.com/ep-683-the-pig-man-of-chino-hills-is-under-your-bed"> <span data-offset-key="fvvrs-0-0"><span data-text= "true">https://deadrabbitradio.libsyn.com/ep-683-the-pig-man-of-chino-hills-is-under-your-bed</span></span></a></div> </div> <div class="DraftEditor-paragraphElement" data-block="true" data-editor="f6cv1" data-offset-key="3bkim-0-0"> <div class= "public-DraftStyleDefault-block public-DraftStyleDefault-ltr" data-offset-key="3bkim-0-0"><span data-offset-key= "3bkim-0-0"><span data-text="true">EP 700 - Harvey Vs. The Monster Of The Mangones! (Pig Man episode)</span></span></div> </div> <div class="DraftEditor-paragraphElement" data-block="true" data-editor="f6cv1" data-offset-key="dvg1q-0-0"> <div class= "public-DraftStyleDefault-block public-DraftStyleDefault-ltr" data-offset-key="dvg1q-0-0"><a class="sc-1bctqj2-0 iUIcXv" href= "https://deadrabbitradio.libsyn.com/ep-700-harvey-vs-the-monster-of-the-mangones"> <span data-offset-key="dvg1q-0-0"><span data-text= "true">https://deadrabbitradio.libsyn.com/ep-700-harvey-vs-the-monster-of-the-mangones</span></span></a></div> </div> <div class="DraftEditor-paragraphElement" data-block="true" data-editor="f6cv1" data-offset-key="cgruk-0-0"> <div class= "public-DraftStyleDefault-block public-DraftStyleDefault-ltr" data-offset-key="cgruk-0-0"><span data-offset-key= "cgruk-0-0"><span data-text="true">EP 914 - Transmorphers: An Interactive Adventure! (Pig Man episode/Turning Into Bigfoot episode)</span></span></div> </div> <div class="DraftEditor-paragraphElement" data-block="true" data-editor="f6cv1" data-offset-key="ej3k5-0-0"> <div class= "public-DraftStyleDefault-block public-DraftStyleDefault-ltr" data-offset-key="ej3k5-0-0"><a class="sc-1bctqj2-0 iUIcXv" href= "https://deadrabbitradio.libsyn.com/ep-914-transmorphers-an-interactive-adventure"> <span data-offset-key="ej3k5-0-0"><span data-text= "true">https://deadrabbitradio.libsyn.com/ep-914-transmorphers-an-interactive-adventure</span></span></a></div> </div> <div class="DraftEditor-paragraphElement" data-block="true" data-editor="f6cv1" data-offset-key="42q90-0-0"> <div class= "public-DraftStyleDefault-block public-DraftStyleDefault-ltr" data-offset-key="42q90-0-0"><span data-offset-key= "42q90-0-0"><span data-text="true">EP 318 - The Amish Vs. Bigfoot! (Turning Into Bigfoot episode)</span></span></div> </div> <div class="DraftEditor-paragraphElement" data-block="true" data-editor="f6cv1" data-offset-key="3eog3-0-0"> <div class= "public-DraftStyleDefault-block public-DraftStyleDefault-ltr" data-offset-key="3eog3-0-0"><a class="sc-1bctqj2-0 iUIcXv" href= "https://deadrabbitradio.libsyn.com/ep-318-the-amish-vs-bigfoot"><span data-offset-key="3eog3-0-0"> <span data-text= "true">https://deadrabbitradio.libsyn.com/ep-318-the-amish-vs-bigfoot</span></span></a></div> </div> <div class="DraftEditor-paragraphElement" data-block="true" data-editor="f6cv1" data-offset-key="1srpm-0-0"> <div class= "public-DraftStyleDefault-block public-DraftStyleDefault-ltr" data-offset-key="1srpm-0-0"><span data-offset-key= "1srpm-0-0"><span data-text="true">EP 53 - Crazy Cryptid Week: The Pope Lick Monster (Circus Freak Train Crash episode)</span></span></div> </div> <div class="DraftEditor-paragraphElement" data-block="true" data-editor="f6cv1" data-offset-key="jgu0-0-0"> <div class= "public-DraftStyleDefault-block public-DraftStyleDefault-ltr" data-offset-key="jgu0-0-0"><a class="sc-1bctqj2-0 iUIcXv" href= "https://deadrabbitradio.libsyn.com/ep-53-crazy-cryptid-week-the-pope-lick-monster"> <span data-offset-key="jgu0-0-0"><span data-text= "true">https://deadrabbitradio.libsyn.com/ep-53-crazy-cryptid-week-the-pope-lick-monster</span></span></a></div> </div> <div class="DraftEditor-paragraphElement" data-block="true" data-editor="f6cv1" data-offset-key="9t20r-0-0"> <div class= "public-DraftStyleDefault-block public-DraftStyleDefault-ltr" data-offset-key="9t20r-0-0"><span data-offset-key= "9t20r-0-0"><span data-text="true">LSD Trip (Inflatable Woman story)</span></span></div> </div> <div class="DraftEditor-paragraphElement" data-block="true" data-editor="f6cv1" data-offset-key="cant0-0-0"> <div class= "public-DraftStyleDefault-block public-DraftStyleDefault-ltr" data-offset-key="cant0-0-0"><a class="sc-1bctqj2-0 iUIcXv" href= "https://imgur.com/a/eTAyiZo"><span data-offset-key= "cant0-0-0"><span data-text= "true">https://imgur.com/a/eTAyiZo</span></span></a></div> </div> <div class="DraftEditor-paragraphElement" data-block="true" data-editor="f6cv1" data-offset-key="ei1vf-0-0"> <div class= "public-DraftStyleDefault-block public-DraftStyleDefault-ltr" data-offset-key="ei1vf-0-0"><span data-offset-key= "ei1vf-0-0"><span data-text="true">Tales of the NORTHFIELD, VERMONT 'PIGMAN' Continue</span></span></div> </div> <div class="DraftEditor-paragraphElement" data-block="true" data-editor="f6cv1" data-offset-key="7698o-0-0"> <div class= "public-DraftStyleDefault-block public-DraftStyleDefault-ltr" data-offset-key="7698o-0-0"><a class="sc-1bctqj2-0 iUIcXv" href= "https://www.phantomsandmonsters.com/2023/05/tale-of-northfield-vermont-pigman.html"> <span data-offset-key="7698o-0-0"><span data-text= "true">https://www.phantomsandmonsters.com/2023/05/tale-of-northfield-vermont-pigman.html</span></span></a></div> </div> <div class="DraftEditor-paragraphElement" data-block="true" data-editor="f6cv1" data-offset-key="96g6k-0-0"> <div class= "public-DraftStyleDefault-block public-DraftStyleDefault-ltr" data-offset-key="96g6k-0-0"><span data-offset-key= "96g6k-0-0"><span data-text="true">Sam Harris</span></span></div> </div> <div class="DraftEditor-paragraphElement" data-block="true" data-editor="f6cv1" data-offset-key="6pnf7-0-0"> <div class= "public-DraftStyleDefault-block public-DraftStyleDefault-ltr" data-offset-key="6pnf7-0-0"><a class="sc-1bctqj2-0 iUIcXv" href= "https://cryptidz.fandom.com/wiki/Sam_Harris"><span data-offset-key="6pnf7-0-0"> <span data-text= "true">https://cryptidz.fandom.com/wiki/Sam_Harris</span></span></a></div> </div> <div class="DraftEditor-paragraphElement" data-block="true" data-editor="f6cv1" data-offset-key="9c4ji-0-0"> <div class= "public-DraftStyleDefault-block public-DraftStyleDefault-ltr" data-offset-key="9c4ji-0-0"><span data-offset-key= "9c4ji-0-0"><span data-text="true">The Totally Creepy Story of the Vermont Pigman</span></span></div> </div> <div class="DraftEditor-paragraphElement" data-block="true" data-editor="f6cv1" data-offset-key="4e3l1-0-0"> <div class= "public-DraftStyleDefault-block public-DraftStyleDefault-ltr" data-offset-key="4e3l1-0-0"><a class="sc-1bctqj2-0 iUIcXv" href= "https://vermonter.com/vermont-pigman/"><span data-offset-key= "4e3l1-0-0"><span data-text= "true">https://vermonter.com/vermont-pigman/</span></span></a></div> </div> <div class="DraftEditor-paragraphElement" data-block="true" data-editor="f6cv1" data-offset-key="44bcl-0-0"> <div class= "public-DraftStyleDefault-block public-DraftStyleDefault-ltr" data-offset-key="44bcl-0-0"><span data-offset-key= "44bcl-0-0"><span data-text="true">The legend of the Northfield Pigman, with folklorist Joseph Citro</span></span></div> </div> <div class="DraftEditor-paragraphElement" data-block="true" data-editor="f6cv1" data-offset-key="5cmuk-0-0"> <div class= "public-DraftStyleDefault-block public-DraftStyleDefault-ltr" data-offset-key="5cmuk-0-0"><a class="sc-1bctqj2-0 iUIcXv" href= "https://www.burlingtonfreepress.com/story/life/2022/10/28/northfield-pigman-joseph-citro-digs-into-the-legend-devils-washbowl-vermont/69590062007/"> <span data-offset-key="5cmuk-0-0"><span data-text= "true">https://www.burlingtonfreepress.com/story/life/2022/10/28/northfield-pigman-joseph-citro-digs-into-the-legend-devils-washbowl-vermont/69590062007/</span></span></a></div> </div> <div class="DraftEditor-paragraphElement" data-block="true" data-editor="f6cv1" data-offset-key="7hbkm-0-0"> <div class= "public-DraftStyleDefault-block public-DraftStyleDefault-ltr" data-offset-key="7hbkm-0-0"><span data-offset-key= "7hbkm-0-0"><span data-text="true">Northfield Pigman Lives</span></span></div> </div> <div class="DraftEditor-paragraphElement" data-block="true" data-editor="f6cv1" data-offset-key="30r1u-0-0"> <div class= "public-DraftStyleDefault-block public-DraftStyleDefault-ltr" data-offset-key="30r1u-0-0"><a class="sc-1bctqj2-0 iUIcXv" href= "https://darntough.com/blogs/the-alternate-stitch/northfield-pigman"> <span data-offset-key="30r1u-0-0"><span data-text= "true">https://darntough.com/blogs/the-alternate-stitch/northfield-pigman</span></span></a></div> </div> <div class="DraftEditor-paragraphElement" data-block="true" data-editor="f6cv1" data-offset-key="fp2ov-0-0"> <div class= "public-DraftStyleDefault-block public-DraftStyleDefault-ltr" data-offset-key="fp2ov-0-0"><span data-offset-key= "fp2ov-0-0"><span data-text="true">Listen to the podcast wherever you listen to podcasts!</span></span></div> </div> <div class="DraftEditor-paragraphElement" data-block="true" data-editor="f6cv1" data-offset-key="f2dgq-0-0"> <div class= "public-DraftStyleDefault-block public-DraftStyleDefault-ltr" data-offset-key="f2dgq-0-0"><span data-offset-key= "f2dgq-0-0"> </span></div> </div> <div class="DraftEditor-paragraphElement" data-block="true" data-editor="f6cv1" data-offset-key="ed6t-0-0"> <div class= "public-DraftStyleDefault-block public-DraftStyleDefault-ltr" data-offset-key="ed6t-0-0"><span data-offset-key= "ed6t-0-0"><span data-text= "true">------------------------------------------------</span></span></div> </div> <div class="DraftEditor-paragraphElement" data-block="true" data-editor="f6cv1" data-offset-key="2p8hi-0-0"> <div class= "public-DraftStyleDefault-block public-DraftStyleDefault-ltr" data-offset-key="2p8hi-0-0"><span data-offset-key= "2p8hi-0-0"><span data-text="true">Logo Art By Ash Black</span></span></div> </div> <div class="DraftEditor-paragraphElement" data-block="true" data-editor="f6cv1" data-offset-key="fveei-0-0"> <div class= "public-DraftStyleDefault-block public-DraftStyleDefault-ltr" data-offset-key="fveei-0-0"><span data-offset-key= "fveei-0-0"><span data-text="true">Opening Song: "Atlantis Attacks"</span></span></div> </div> <div class="DraftEditor-paragraphElement" data-block="true" data-editor="f6cv1" data-offset-key="260lr-0-0"> <div class= "public-DraftStyleDefault-block public-DraftStyleDefault-ltr" data-offset-key="260lr-0-0"><span data-offset-key= "260lr-0-0"><span data-text="true">Closing Song: "Bella Royale"</span></span></div> </div> <div class="DraftEditor-paragraphElement" data-block="true" data-editor="f6cv1" data-offset-key="cmdka-0-0"> <div class= "public-DraftStyleDefault-block public-DraftStyleDefault-ltr" data-offset-key="cmdka-0-0"><span data-offset-key= "cmdka-0-0"><span data-text="true">Music By Simple</span></span></div> </div> <div class="DraftEditor-paragraphElement" data-block="true" data-editor="f6cv1" data-offset-key="89hai-0-0"> <div class= "public-DraftStyleDefault-block public-DraftStyleDefault-ltr" data-offset-key="89hai-0-0"><span data-offset-key= "89hai-0-0"><span data-text="true">Rabbitron 3000 created by Eerbud</span></span></div> </div> <div class="DraftEditor-paragraphElement" data-block="true" data-editor="f6cv1" data-offset-key="470i4-0-0"> <div class= "public-DraftStyleDefault-block public-DraftStyleDefault-ltr" data-offset-key="470i4-0-0"><span data-offset-key= "470i4-0-0"><span data-text="true">Thanks to Chris K, Founder Of The Golden Rabbit Brigade</span></span></div> </div> <div class="DraftEditor-paragraphElement" data-block="true" data-editor="f6cv1" data-offset-key="71skd-0-0"> <div class= "public-DraftStyleDefault-block public-DraftStyleDefault-ltr" data-offset-key="71skd-0-0"><span data-offset-key= "71skd-0-0"><span data-text="true">Dead Rabbit Archivist Some Weirdo On Twitter AKA Jack</span></span></div> </div> <div class="DraftEditor-paragraphElement" data-block="true" data-editor="f6cv1" data-offset-key="644vm-0-0"> <div class= "public-DraftStyleDefault-block public-DraftStyleDefault-ltr" data-offset-key="644vm-0-0"><span data-offset-key= "644vm-0-0"><span data-text="true">YouTube Champ Stewart Meatball</span></span></div> </div> <div class="DraftEditor-paragraphElement" data-block="true" data-editor="f6cv1" data-offset-key="as4hr-0-0"> <div class= "public-DraftStyleDefault-block public-DraftStyleDefault-ltr" data-offset-key="as4hr-0-0"><span data-offset-key= "as4hr-0-0"><span data-text="true">The Haunted Mic Arm provided by Chyme Chili</span></span></div> </div> <div class="DraftEditor-paragraphElement" data-block="true" data-editor="f6cv1" data-offset-key="5m93v-0-0"> <div class= "public-DraftStyleDefault-block public-DraftStyleDefault-ltr" data-offset-key="5m93v-0-0"><span data-offset-key= "5m93v-0-0"><span data-text="true">The Golden Rabbit Army: Fabio N, Chyme Chili, Greg Gourley, Vexing</span></span></div> </div> <div class="DraftEditor-paragraphElement" data-block="true" data-editor="f6cv1" data-offset-key="a982q-0-0"> <div class= "public-DraftStyleDefault-block public-DraftStyleDefault-ltr" data-offset-key="a982q-0-0"><span data-offset-key= "a982q-0-0"><span data-text="true">Wiki by Germ</span></span></div> </div> <div class="DraftEditor-paragraphElement" data-block="true" data-editor="f6cv1" data-offset-key="fiufo-0-0"> <div class= "public-DraftStyleDefault-block public-DraftStyleDefault-ltr" data-offset-key="fiufo-0-0"><a class="sc-1bctqj2-0 iUIcXv" href= "http://www.deadrabbit.com/"><span data-offset-key= "fiufo-0-0"><span data-text= "true">http://www.DeadRabbit.com</span></span></a></div> </div> <div class="DraftEditor-paragraphElement" data-block="true" data-editor="f6cv1" data-offset-key="67fpa-0-0"> <div class= "public-DraftStyleDefault-block public-DraftStyleDefault-ltr" data-offset-key="67fpa-0-0"><span data-offset-key= "67fpa-0-0"><span data-text="true">Email:</span></span> <a class= "sc-1bctqj2-0 iUIcXv" href= "mailto:DeadRabbitRadio@gmail.com"><span data-offset-key= "67fpa-1-0"><span data-text= "true">DeadRabbitRadio@gmail.com</span></span></a></div> </div> <div class="DraftEditor-paragraphElement" data-block="true" data-editor="f6cv1" data-offset-key="du13s-0-0"> <div class= "public-DraftStyleDefault-block public-DraftStyleDefault-ltr" data-offset-key="du13s-0-0"><span data-offset-key= "du13s-0-0"><span data-text="true">Twitter: @DeadRabbitRadio</span></span></div> </div> <div class="DraftEditor-paragraphElement" data-block="true" data-editor="f6cv1" data-offset-key="5ntj5-0-0"> <div class= "public-DraftStyleDefault-block public-DraftStyleDefault-ltr" data-offset-key="5ntj5-0-0"><span data-offset-key= "5ntj5-0-0"><span data-text="true">Facebook:</span></span> <a class="sc-1bctqj2-0 iUIcXv" href= "http://www.facebook.com/DeadRabbitRadio"><span data-offset-key= "5ntj5-1-0"><span data-text= "true">www.Facebook.com/DeadRabbitRadio</span></span></a></div> </div> <div class="DraftEditor-paragraphElement" data-block="true" data-editor="f6cv1" data-offset-key="7rn0j-0-0"> <div class= "public-DraftStyleDefault-block public-DraftStyleDefault-ltr" data-offset-key="7rn0j-0-0"><span data-offset-key= "7rn0j-0-0"><span data-text="true">TikTok:</span></span> <a class= "sc-1bctqj2-0 iUIcXv" href= "https://www.tiktok.com/@deadrabbitradio"><span data-offset-key= "7rn0j-1-0"><span data-text= "true">https://www.tiktok.com/@deadrabbitradio</span></span></a></div> </div> <div class="DraftEditor-paragraphElement" data-block="true" data-editor="f6cv1" data-offset-key="9fdkf-0-0"> <div class= "public-DraftStyleDefault-block public-DraftStyleDefault-ltr" data-offset-key="9fdkf-0-0"><span data-offset-key= "9fdkf-0-0"><span data-text="true">Dead Rabbit Radio Subreddit:</span></span> <a class="sc-1bctqj2-0 iUIcXv" href= "https://www.reddit.com/r/DeadRabbitRadio/"><span data-offset-key= "9fdkf-1-0"><span data-text= "true">https://www.reddit.com/r/DeadRabbitRadio/</span></span></a></div> </div> <div class="DraftEditor-paragraphElement" data-block="true" data-editor="f6cv1" data-offset-key="abdrq-0-0"> <div class= "public-DraftStyleDefault-block public-DraftStyleDefault-ltr" data-offset-key="abdrq-0-0"><span data-offset-key= "abdrq-0-0"><span data-text="true">Paranormal News Subreddit:</span></span> <a class="sc-1bctqj2-0 iUIcXv" href= "https://www.reddit.com/r/ParanormalNews/"><span data-offset-key= "abdrq-1-0"><span data-text= "true">https://www.reddit.com/r/ParanormalNews/</span></span></a></div> </div> <div class="DraftEditor-paragraphElement" data-block="true" data-editor="f6cv1" data-offset-key="ff84f-0-0"> <div class= "public-DraftStyleDefault-block public-DraftStyleDefault-ltr" data-offset-key="ff84f-0-0"><span data-offset-key= "ff84f-0-0"><span data-text="true">Mailing Address:</span></span></div> </div> <div class="DraftEditor-paragraphElement" data-block="true" data-editor="f6cv1" data-offset-key="c8a1l-0-0"> <div class= "public-DraftStyleDefault-block public-DraftStyleDefault-ltr" data-offset-key="c8a1l-0-0"><span data-offset-key= "c8a1l-0-0"><span data-text="true">Jason Carpenter</span></span></div> </div> <div class="DraftEditor-paragraphElement" data-block="true" data-editor="f6cv1" data-offset-key="aphvr-0-0"> <div class= "public-DraftStyleDefault-block public-DraftStyleDefault-ltr" data-offset-key="aphvr-0-0"><span data-offset-key= "aphvr-0-0"><span data-text="true">PO Box 1363</span></span></div> </div> <div class="DraftEditor-paragraphElement" data-block="true" data-editor="f6cv1" data-offset-key="8h6t7-0-0"> <div class= "public-DraftStyleDefault-block public-DraftStyleDefault-ltr" data-offset-key="8h6t7-0-0"><span data-offset-key= "8h6t7-0-0"><span data-text="true">Hood River, OR 97031</span></span></div> </div> <div class="DraftEditor-paragraphElement" data-block="true" data-editor="f6cv1" data-offset-key="9t163-0-0"> <div class= "public-DraftStyleDefault-block public-DraftStyleDefault-ltr" data-offset-key="9t163-0-0"><span data-offset-key= "9t163-0-0"><span data-text="true">Paranormal, Conspiracy, and True Crime news as it happens! Jason Carpenter breaks the stories they'll be talking about tomorrow, assuming the world doesn't end today.</span></span></div> </div> <div class="DraftEditor-paragraphElement" data-block="true" data-editor="f6cv1" data-offset-key="2dpuk-0-0"> <div class= "public-DraftStyleDefault-block public-DraftStyleDefault-ltr" data-offset-key="2dpuk-0-0"><span data-offset-key= "2dpuk-0-0"><span data-text="true">All Contents Of This Podcast Copyright Jason Carpenter 2018 – 2023</span></span></div> </div>]]></description>
  <content:encoded><![CDATA[ A woman deflates/The Northfield Pigman attacks!       Vote For Your Favorite Paranormal Podcast: Dead Rabbit Radio!   <a class="sc-1bctqj2-0 iUIcXv" href= "https://paranormalitymag.com/vote25/">https://paranormalitymag.com/vote25/</a>   Patreon   <a class="sc-1bctqj2-0 iUIcXv" href= "https://www.patreon.com/user?u=18482113">https://www.patreon.com/user?u=18482113</a>   PayPal Donation Link   <a class="sc-1bctqj2-0 iUIcXv" href= "https://tinyurl.com/mrxe36ph">https://tinyurl.com/mrxe36ph</a>   MERCH STORE!!!   <a class="sc-1bctqj2-0 iUIcXv" href= "https://tinyurl.com/y8zam4o2">https://tinyurl.com/y8zam4o2</a>   Amazon Wish List   <a class="sc-1bctqj2-0 iUIcXv" href= "https://www.amazon.com/hz/wishlist/ls/28CIOGSFRUXAD?ref_=wl_share"> https://www.amazon.com/hz/wishlist/ls/28CIOGSFRUXAD?ref_=wl_share</a>   Dead Rabbit Radio Wiki   <a class="sc-1bctqj2-0 iUIcXv" href= "https://deadrabbitradio.pods.monster/doku.php?id=Welcome"> https://deadrabbitradio.pods.monster/doku.php?id=Welcome</a>       Help Promote Dead Rabbit!   Dual Flyer   <a class="sc-1bctqj2-0 iUIcXv" href= "https://i.imgur.com/OhuoI2v.jpg">https://i.imgur.com/OhuoI2v.jpg</a>   "As Above" Flyer   <a class="sc-1bctqj2-0 iUIcXv" href= "https://i.imgur.com/yobMtUp.jpg">https://i.imgur.com/yobMtUp.jpg</a>   “Alien Flyer” By TVP VT U   <a class="sc-1bctqj2-0 iUIcXv" href= "https://imgur.com/gallery/aPN1Fnw">https://imgur.com/gallery/aPN1Fnw</a>   “QR Code Flyer” by Finn   <a class="sc-1bctqj2-0 iUIcXv" href= "https://imgur.com/a/aYYUMAh">https://imgur.com/a/aYYUMAh</a>       Links:   EP 310 - The Curse Of The Pigman: An Interactive Adventure! (Pig Man episode)   <a class="sc-1bctqj2-0 iUIcXv" href= "https://deadrabbitradio.libsyn.com/ep-310-the-curse-of-the-pigman-an-interactive-adventure"> https://deadrabbitradio.libsyn.com/ep-310-the-curse-of-the-pigman-an-interactive-adventure</a>   EP 488 - Attack Of The Pig Lady! (Pig Man episode)   <a class="sc-1bctqj2-0 iUIcXv" href= "https://deadrabbitradio.libsyn.com/ep-488-attack-of-the-pig-lady"> https://deadrabbitradio.libsyn.com/ep-488-attack-of-the-pig-lady</a>   EP 683 - The Pig Man Of Chino Hills Is Under Your Bed!   <a class="sc-1bctqj2-0 iUIcXv" href= "https://deadrabbitradio.libsyn.com/ep-683-the-pig-man-of-chino-hills-is-under-your-bed"> https://deadrabbitradio.libsyn.com/ep-683-the-pig-man-of-chino-hills-is-under-your-bed</a>   EP 700 - Harvey Vs. The Monster Of The Mangones! (Pig Man episode)   <a class="sc-1bctqj2-0 iUIcXv" href= "https://deadrabbitradio.libsyn.com/ep-700-harvey-vs-the-monster-of-the-mangones"> https://deadrabbitradio.libsyn.com/ep-700-harvey-vs-the-monster-of-the-mangones</a>   EP 914 - Transmorphers: An Interactive Adventure! (Pig Man episode/Turning Into Bigfoot episode)   <a class="sc-1bctqj2-0 iUIcXv" href= "https://deadrabbitradio.libsyn.com/ep-914-transmorphers-an-interactive-adventure"> https://deadrabbitradio.libsyn.com/ep-914-transmorphers-an-interactive-adventure</a>   EP 318 - The Amish Vs. Bigfoot! (Turning Into Bigfoot episode)   <a class="sc-1bctqj2-0 iUIcXv" href= "https://deadrabbitradio.libsyn.com/ep-318-the-amish-vs-bigfoot"> https://deadrabbitradio.libsyn.com/ep-318-the-amish-vs-bigfoot</a>   EP 53 - Crazy Cryptid Week: The Pope Lick Monster (Circus Freak Train Crash episode)   <a class="sc-1bctqj2-0 iUIcXv" href= "https://deadrabbitradio.libsyn.com/ep-53-crazy-cryptid-week-the-pope-lick-monster"> https://deadrabbitradio.libsyn.com/ep-53-crazy-cryptid-week-the-pope-lick-monster</a>   LSD Trip (Inflatable Woman story)   <a class="sc-1bctqj2-0 iUIcXv" href= "https://imgur.com/a/eTAyiZo">https://imgur.com/a/eTAyiZo</a>   Tales of the NORTHFIELD, VERMONT 'PIGMAN' Continue   <a class="sc-1bctqj2-0 iUIcXv" href= "https://www.phantomsandmonsters.com/2023/05/tale-of-northfield-vermont-pigman.html"> https://www.phantomsandmonsters.com/2023/05/tale-of-northfield-vermont-pigman.html</a>   Sam Harris   <a class="sc-1bctqj2-0 iUIcXv" href= "https://cryptidz.fandom.com/wiki/Sam_Harris"> https://cryptidz.fandom.com/wiki/Sam_Harris</a>   The Totally Creepy Story of the Vermont Pigman   <a class="sc-1bctqj2-0 iUIcXv" href= "https://vermonter.com/vermont-pigman/">https://vermonter.com/vermont-pigman/</a>   The legend of the Northfield Pigman, with folklorist Joseph Citro   <a class="sc-1bctqj2-0 iUIcXv" href= "https://www.burlingtonfreepress.com/story/life/2022/10/28/northfield-pigman-joseph-citro-digs-into-the-legend-devils-washbowl-vermont/69590062007/"> https://www.burlingtonfreepress.com/story/life/2022/10/28/northfield-pigman-joseph-citro-digs-into-the-legend-devils-washbowl-vermont/69590062007/</a>   Northfield Pigman Lives   <a class="sc-1bctqj2-0 iUIcXv" href= "https://darntough.com/blogs/the-alternate-stitch/northfield-pigman"> https://darntough.com/blogs/the-alternate-stitch/northfield-pigman</a>   Listen to the podcast wherever you listen to podcasts!       ------------------------------------------------   Logo Art By Ash Black   Opening Song: "Atlantis Attacks"   Closing Song: "Bella Royale"   Music By Simple   Rabbitron 3000 created by Eerbud   Thanks to Chris K, Founder Of The Golden Rabbit Brigade   Dead Rabbit Archivist Some Weirdo On Twitter AKA Jack   YouTube Champ Stewart Meatball   The Haunted Mic Arm provided by Chyme Chili   The Golden Rabbit Army: Fabio N, Chyme Chili, Greg Gourley, Vexing   Wiki by Germ   <a class="sc-1bctqj2-0 iUIcXv" href= "http://www.deadrabbit.com/">http://www.DeadRabbit.com</a>   Email: <a class= "sc-1bctqj2-0 iUIcXv" href= "mailto:DeadRabbitRadio@gmail.com">DeadRabbitRadio@gmail.com</a>   Twitter: @DeadRabbitRadio   Facebook: <a class="sc-1bctqj2-0 iUIcXv" href= "http://www.facebook.com/DeadRabbitRadio">www.Facebook.com/DeadRabbitRadio</a>   TikTok: <a class= "sc-1bctqj2-0 iUIcXv" href= "https://www.tiktok.com/@deadrabbitradio">https://www.tiktok.com/@deadrabbitradio</a>   Dead Rabbit Radio Subreddit: <a class="sc-1bctqj2-0 iUIcXv" href= "https://www.reddit.com/r/DeadRabbitRadio/">https://www.reddit.com/r/DeadRabbitRadio/</a>   Paranormal News Subreddit: <a class="sc-1bctqj2-0 iUIcXv" href= "https://www.reddit.com/r/ParanormalNews/">https://www.reddit.com/r/ParanormalNews/</a>   Mailing Address:   Jason Carpenter   PO Box 1363   Hood River, OR 97031   Paranormal, Conspiracy, and True Crime news as it happens! Jason Carpenter breaks the stories they'll be talking about tomorrow, assuming the world doesn't end today.   All Contents Of This Podcast Copyright Jason Carpenter 2018 – 2023 ]]></content:encoded>
  <enclosure length="43908455" type="audio/mpeg" url="https://chtbl.com/track/E2D25/dts.podtrac.com/redirect.mp3/pdcn.co/e/traffic.libsyn.com/secure/deadrabbitradio/EP_1083_-_Vermont_Pigman_COMP_WD_Ad.mp3?dest-id=877154"/>
  <itunes:duration>45:45</itunes:duration>
  <itunes:explicit>false</itunes:explicit>
  <itunes:keywords/>
  <itunes:subtitle><![CDATA[A woman deflates/The Northfield Pigman attacks!       Vote For Your Favorite Paranormal Podcast: Dead Rabbit Radio!      Patreon      PayPal Donation Link      MERCH STORE!!!      Amazon Wish List      Dead Rabbit Radio Wiki          Help...]]></itunes:subtitle>
  <itunes:season>21</itunes:season>
  <itunes:episode>1083</itunes:episode>
  <itunes:episodeType>full</itunes:episodeType>
  <itunes:author>Jason Carpenter</itunes:author>
</item>