<item>
  <title>The Classics EP 22 - The Multiverse Abides</title>
  <itunes:title>The Classics  - The Multiverse Abides</itunes:title>
  <pubDate>Wed, 21 Oct 2020 00:35:37 +0000</pubDate>
  <guid isPermaLink="false"><![CDATA[03adbfcd-f1fd-46e7-81a3-0355dbafcb66]]></guid>
  <link><![CDATA[https://sites.libsyn.com/140084/the-classics-ep-22-the-multiverse-abides]]></link>
  <itunes:image href="https://ssl-static.libsyn.com/p/assets/4/a/9/4/4a9498a386e5d95d/OG_Itunes_3000_72.jpg"/>
  <description><![CDATA[<p>Today we visit Trump to talk about aliens and then meet a man who tumbled through the multiverse after a near-death experience!</p> <p>Patreon </p> <p><a href= "https://www.patreon.com/user?u=18482113">https://www.patreon.com/user?u=18482113</a></p> <p> </p> <p>MERCH STORE!!!</p> <p><a href= "https://www.redbubble.com/people/deadrabbitradio/works/35749420-dead-rabbit-radio?asc=u"> https://www.redbubble.com/people/deadrabbitradio/works/35749420-dead-rabbit-radio?asc=u</a></p> <p> </p> <p>Links:</p> <p>Trump says he'll 'take a good, strong look' at whether UFOs exist</p> <p><a href= "https://www.insider.com/donald-trump-ufos-pentagon-task-force-exist-2020-10"> https://www.insider.com/donald-trump-ufos-pentagon-task-force-exist-2020-10</a></p> <p>Trump says he doesn't particularly believe in UFOs</p> <p><a href= "https://www.youtube.com/watch?v=YDom6wNYb9w">https://www.youtube.com/watch?v=YDom6wNYb9w</a></p> <p>Trump got a briefing on UFOs, but said he doesn't 'particularly' believe in them</p> <p><a href= "https://www.usatoday.com/story/news/politics/2019/06/15/trump-briefed-ufos-but-doesnt-particularly-believe-them/1465077001/"> https://www.usatoday.com/story/news/politics/2019/06/15/trump-briefed-ufos-but-doesnt-particularly-believe-them/1465077001/</a></p> <p>Wilson FDE NDERF</p> <p><a href= "https://www.nderf.org/Experiences/1wilson_fde.html">https://www.nderf.org/Experiences/1wilson_fde.html</a></p> <p> </p> <p>Listen to the daily podcast anywhere you listen to podcasts!</p> <p>------------------------------------------------</p> <p>Logo Art By Ash Black</p> <p>Opening Song: "Atlantis Attacks"</p> <p>Closing Song: "Bella Royale"</p> <p>Music By Dr. Huxxxtable</p> <p>Rabbitron 3000 created by Eerbud</p> <p>Thanks to Chris K, Founder Of The Golden Rabbit Brigade</p> <p>Dead Rabbit Archivist Some Weirdo On Twitter AKA Jack</p> <p> </p> <p><a href= "http://www.DeadRabbit.com">http://www.DeadRabbit.com</a></p> <p>Email: <a href= "mailto:DeadRabbitRadio@gmail.com">DeadRabbitRadio@gmail.com</a></p> <p>Twitter: @DeadRabbitRadio</p> <p>Facebook: <a href= "http://www.Facebook.com/DeadRabbitRadio">www.Facebook.com/DeadRabbitRadio</a></p> <p> </p> <p>Paranormal, Conspiracy, and True Crime news as it happens! Jason Carpenter breaks the stories they'll be talking about tomorrow, assuming the world doesn't end today.</p> <p> </p> <p>All Contents Of This Podcast Copyright Jason Carpenter 2018 - 2020</p>]]></description>
  <content:encoded><![CDATA[<p>Today we visit Trump to talk about aliens and then meet a man who tumbled through the multiverse after a near-death experience!</p> <p>Patreon </p> <p><a href= "https://www.patreon.com/user?u=18482113">https://www.patreon.com/user?u=18482113</a></p> <p> </p> <p>MERCH STORE!!!</p> <p><a href= "https://www.redbubble.com/people/deadrabbitradio/works/35749420-dead-rabbit-radio?asc=u"> https://www.redbubble.com/people/deadrabbitradio/works/35749420-dead-rabbit-radio?asc=u</a></p> <p> </p> <p>Links:</p> <p>Trump says he'll 'take a good, strong look' at whether UFOs exist</p> <p><a href= "https://www.insider.com/donald-trump-ufos-pentagon-task-force-exist-2020-10"> https://www.insider.com/donald-trump-ufos-pentagon-task-force-exist-2020-10</a></p> <p>Trump says he doesn't particularly believe in UFOs</p> <p><a href= "https://www.youtube.com/watch?v=YDom6wNYb9w">https://www.youtube.com/watch?v=YDom6wNYb9w</a></p> <p>Trump got a briefing on UFOs, but said he doesn't 'particularly' believe in them</p> <p><a href= "https://www.usatoday.com/story/news/politics/2019/06/15/trump-briefed-ufos-but-doesnt-particularly-believe-them/1465077001/"> https://www.usatoday.com/story/news/politics/2019/06/15/trump-briefed-ufos-but-doesnt-particularly-believe-them/1465077001/</a></p> <p>Wilson FDE NDERF</p> <p><a href= "https://www.nderf.org/Experiences/1wilson_fde.html">https://www.nderf.org/Experiences/1wilson_fde.html</a></p> <p> </p> <p>Listen to the daily podcast anywhere you listen to podcasts!</p> <p>------------------------------------------------</p> <p>Logo Art By Ash Black</p> <p>Opening Song: "Atlantis Attacks"</p> <p>Closing Song: "Bella Royale"</p> <p>Music By Dr. Huxxxtable</p> <p>Rabbitron 3000 created by Eerbud</p> <p>Thanks to Chris K, Founder Of The Golden Rabbit Brigade</p> <p>Dead Rabbit Archivist Some Weirdo On Twitter AKA Jack</p> <p> </p> <p><a href= "http://www.DeadRabbit.com">http://www.DeadRabbit.com</a></p> <p>Email: <a href= "mailto:DeadRabbitRadio@gmail.com">DeadRabbitRadio@gmail.com</a></p> <p>Twitter: @DeadRabbitRadio</p> <p>Facebook: <a href= "http://www.Facebook.com/DeadRabbitRadio">www.Facebook.com/DeadRabbitRadio</a></p> <p> </p> <p>Paranormal, Conspiracy, and True Crime news as it happens! Jason Carpenter breaks the stories they'll be talking about tomorrow, assuming the world doesn't end today.</p> <p> </p> <p>All Contents Of This Podcast Copyright Jason Carpenter 2018 - 2020</p>]]></content:encoded>
  <enclosure length="48179592" type="audio/mpeg" url="https://chtbl.com/track/E2D25/dts.podtrac.com/redirect.mp3/pdcn.co/e/traffic.libsyn.com/secure/deadrabbitradio/CLASSICS_022_-_The_Multiverse_Abides.mp3?dest-id=877154"/>
  <itunes:duration>50:12</itunes:duration>
  <itunes:explicit>false</itunes:explicit>
  <itunes:keywords/>
  <itunes:subtitle><![CDATA[Today we visit Trump to talk about aliens and then meet a man who tumbled through the multiverse after a near-death experience! Patreon     MERCH STORE!!!    Links: Trump says he'll 'take a good, strong look' at whether UFOs exist ...]]></itunes:subtitle>
  <itunes:episode>22</itunes:episode>
  <itunes:episodeType>full</itunes:episodeType>
  <itunes:author>Jason Carpenter</itunes:author>
</item>